ampoule/__init__.py
ampoule/_version.py
ampoule/child.py
ampoule/commands.py
ampoule/iampoule.py
ampoule/main.py
ampoule/pool.py
ampoule/rpool.py
ampoule/service.py
ampoule/util.py
ampoule/test/__init__.py
ampoule/test/test_process.py
ampoule/test/test_proxy.py
ampoule-24.10.0.dist-info/COPYING.txt
ampoule-24.10.0.dist-info/METADATA
ampoule-24.10.0.dist-info/WHEEL
ampoule-24.10.0.dist-info/top_level.txt
ampoule-24.10.0.dist-info/RECORD
