Metadata-Version: 2.1
Name: ampoule
Version: 24.10.0
Summary: A process pool built on Twisted and AMP.
Home-page: https://github.com/twisted/ampoule
Author: Valentino Volonghi
Author-email: dialtone@gmail.com
Maintainer: Glyph Lefkowitz
Maintainer-email: glyph@twistedmatrix.com
License: MIT License
Classifier: Development Status :: 4 - Beta
Classifier: Environment :: Console
Classifier: Intended Audience :: Developers
Classifier: License :: OSI Approved :: MIT License
Classifier: Natural Language :: English
Classifier: Programming Language :: Python
Classifier: Programming Language :: Python :: 3
Classifier: Programming Language :: Python :: 3.7
Classifier: Programming Language :: Python :: 3.8
Classifier: Programming Language :: Python :: 3.9
Classifier: Programming Language :: Python :: 3.10
Classifier: Programming Language :: Python :: 3.11
Classifier: Programming Language :: Python :: 3.12
Classifier: Programming Language :: Python :: 3.13
Classifier: Topic :: System
Requires-Python: >=3
License-File: COPYING.txt
Requires-Dist: Twisted[tls] >=17
Requires-Dist: incremental
